fastcs_catio/README.txt
fastcs_catio/__init__.py
fastcs_catio/__main__.py
fastcs_catio/_constants.py
fastcs_catio/_types.py
fastcs_catio/_version.py
fastcs_catio/catio_attribute_io.py
fastcs_catio/catio_connection.py
fastcs_catio/catio_controller.py
fastcs_catio/catio_controller.yaml
fastcs_catio/catio_hardware.py
fastcs_catio/client.py
fastcs_catio/devices.py
fastcs_catio/messages.py
fastcs_catio/schema.json
fastcs_catio/symbols.py
fastcs_catio/utils.py
fastcs_catio-1.1a3.dist-info/licenses/LICENSE
fastcs_catio-1.1a3.dist-info/METADATA
fastcs_catio-1.1a3.dist-info/WHEEL
fastcs_catio-1.1a3.dist-info/entry_points.txt
fastcs_catio-1.1a3.dist-info/top_level.txt
fastcs_catio-1.1a3.dist-info/RECORD
