Metadata-Version: 2.4
Name: fastcs-catio
Version: 1.1a3
Summary: Control system integration of EtherCAT I/O devices running under TwinCAT using pyads and FastCS
Author-email: Greg Gay <gregory.gay@diamond.ac.uk>
License:                                  Apache License
Project-URL: GitHub, https://github.com/DiamondLightSource/fastcs-catio
Classifier: Development Status :: 3 - Alpha
Classifier: License :: OSI Approved :: Apache Software License
Classifier: Programming Language :: Python :: 3.11
Classifier: Programming Language :: Python :: 3.12
Classifier: Programming Language :: Python :: 3.13
Requires-Python: >=3.11
License-File: LICENSE
Requires-Dist: typing-extensions; python_version < "3.8"
Requires-Dist: numpy
Requires-Dist: pvi
Requires-Dist: typer
Requires-Dist: fastcs[epics]==0.12.0a1
Requires-Dist: softioc>=4.7.0
Dynamic: license-file
